{"width": 15, "squares": [{"num": 1, "solution": "L"}, {"num": 2, "solution": "O"}, {"num": 3, "solution": "G"}, {"num": 4, "solution": "E"}, {"num": -1, "solution": ""}, {"num": 5, "solution": "I"}, {"num": 6, "solution": "P"}, {"num": 7, "solution": "A"}, {"num": 8, "solution": "S"}, {"num": 9, "solution": "S"}, {"num": -1, "solution": ""}, {"num": 10, "solution": "T"}, {"num": 11, "solution": "W"}, {"num": 12, "solution": "O"}, {"num": 13, "solution": "S"}, {"num": 14, "solution": "O"}, {"num": 0, "solution": "B"}, {"num": 0, "solution": "I"}, {"num": 0, "solution": "T"}, {"num": -1, "solution": ""}, {"num": 15, "solution": "N"}, {"num": 0, "solution": "O"}, {"num": 0, "solution": "R"}, {"num": 0, "solution": "T"}, {"num": 0, "solution": "E"}, {"num": -1, "solution": ""}, {"num": 16, "solution": "O"}, {"num": 0, "solution": "A"}, {"num": 0, "solution": "T"}, {"num": 0, "solution": "H"}, {"num": 17, "solution": "E"}, {"num": 0, "solution": "E"}, {"num": 0, "solution": "R"}, {"num": 0, "solution": "O"}, {"num": -1, "solution": ""}, {"num": 18, "solution": "M"}, {"num": 0, "solution": "O"}, {"num": 0, "solution": "B"}, {"num": 0, "solution": "I"}, {"num": 0, "solution": "L"}, {"num": -1, "solution": ""}, {"num": 19, "solution": "M"}, {"num": 0, "solution": "U"}, {"num": 0, "solution": "S"}, {"num": 0, "solution": "E"}, {"num": 20, "solution": "S"}, {"num": 0, "solution": "Y"}, {"num": 0, "solution": "D"}, {"num": 0, "solution": "N"}, {"num": 21, "solution": "E"}, {"num": 0, "solution": "Y"}, {"num": 0, "solution": "P"}, {"num": 0, "solution": "O"}, {"num": 0, "solution": "L"}, {"num": 0, "solution": "L"}, {"num": 22, "solution": "A"}, {"num": 0, "solution": "C"}, {"num": 0, "solution": "K"}, {"num": -1, "solution": ""}, {"num": -1, "solution": ""}, {"num": 23, "solution": "S"}, {"num": 0, "solution": "E"}, {"num": 0, "solution": "L"}, {"num": 0, "solution": "I"}, {"num": 0, "solution": "G"}, {"num": -1, "solution": ""}, {"num": 24, "solution": "E"}, {"num": 0, "solution": "R"}, {"num": 0, "solution": "E"}, {"num": -1, "solution": ""}, {"num": 25, "solution": "G"}, {"num": 0, "solution": "A"}, {"num": 0, "solution": "E"}, {"num": 26, "solution": "L"}, {"num": 27, "solution": "S"}, {"num": -1, "solution": ""}, {"num": 28, "solution": "R"}, {"num": 0, "solution": "E"}, {"num": 0, "solution": "A"}, {"num": 0, "solution": "R"}, {"num": 29, "solution": "E"}, {"num": 0, "solution": "D"}, {"num": -1, "solution": ""}, {"num": 30, "solution": "T"}, {"num": 31, "solution": "O"}, {"num": 0, "solution": "O"}, {"num": 0, "solution": "T"}, {"num": 0, "solution": "S"}, {"num": 0, "solution": "I"}, {"num": 0, "solution": "E"}, {"num": -1, "solution": ""}, {"num": -1, "solution": ""}, {"num": -1, "solution": ""}, {"num": 32, "solution": "N"}, {"num": 0, "solution": "E"}, {"num": 0, "solution": "V"}, {"num": -1, "solution": ""}, {"num": 33, "solution": "C"}, {"num": 0, "solution": "T"}, {"num": 0, "solution": "R"}, {"num": -1, "solution": ""}, {"num": -1, "solution": ""}, {"num": 34, "solution": "H"}, {"num": 0, "solution": "O"}, {"num": 0, "solution": "T"}, {"num": -1, "solution": ""}, {"num": 35, "solution": "D"}, {"num": 36, "solution": "U"}, {"num": 0, "solution": "S"}, {"num": 0, "solution": "T"}, {"num": 0, "solution": "I"}, {"num": 37, "solution": "N"}, {"num": 0, "solution": "H"}, {"num": 0, "solution": "O"}, {"num": 0, "solution": "F"}, {"num": 38, "solution": "F"}, {"num": 39, "solution": "M"}, {"num": 0, "solution": "A"}, {"num": 0, "solution": "N"}, {"num": -1, "solution": ""}, {"num": 40, "solution": "B"}, {"num": 0, "solution": "E"}, {"num": 0, "solution": "N"}, {"num": -1, "solution": ""}, {"num": -1, "solution": ""}, {"num": 41, "solution": "T"}, {"num": 0, "solution": "I"}, {"num": 0, "solution": "E"}, {"num": -1, "solution": ""}, {"num": 42, "solution": "E"}, {"num": 0, "solution": "E"}, {"num": 0, "solution": "O"}, {"num": -1, "solution": ""}, {"num": -1, "solution": ""}, {"num": -1, "solution": ""}, {"num": 43, "solution": "R"}, {"num": 0, "solution": "A"}, {"num": 0, "solution": "I"}, {"num": 44, "solution": "N"}, {"num": 45, "solution": "M"}, {"num": 0, "solution": "A"}, {"num": 0, "solution": "N"}, {"num": -1, "solution": ""}, {"num": 46, "solution": "T"}, {"num": 0, "solution": "O"}, {"num": 0, "solution": "R"}, {"num": 0, "solution": "M"}, {"num": 47, "solution": "E"}, {"num": 48, "solution": "S"}, {"num": -1, "solution": ""}, {"num": 49, "solution": "A"}, {"num": 0, "solution": "R"}, {"num": 0, "solution": "M"}, {"num": 0, "solution": "E"}, {"num": 0, "solution": "E"}, {"num": -1, "solution": ""}, {"num": 50, "solution": "N"}, {"num": 51, "solution": "A"}, {"num": 0, "solution": "H"}, {"num": -1, "solution": ""}, {"num": 52, "solution": "M"}, {"num": 0, "solution": "E"}, {"num": 0, "solution": "N"}, {"num": 0, "solution": "L"}, {"num": 53, "solution": "O"}, {"num": -1, "solution": ""}, {"num": -1, "solution": ""}, {"num": 54, "solution": "B"}, {"num": 0, "solution": "A"}, {"num": 0, "solution": "R"}, {"num": 55, "solution": "R"}, {"num": 0, "solution": "Y"}, {"num": 0, "solution": "L"}, {"num": 0, "solution": "E"}, {"num": 56, "solution": "V"}, {"num": 0, "solution": "I"}, {"num": 0, "solution": "N"}, {"num": 0, "solution": "S"}, {"num": 0, "solution": "O"}, {"num": 0, "solution": "N"}, {"num": 57, "solution": "S"}, {"num": 58, "solution": "L"}, {"num": 0, "solution": "U"}, {"num": 0, "solution": "R"}, {"num": -1, "solution": ""}, {"num": 59, "solution": "B"}, {"num": 0, "solution": "I"}, {"num": 0, "solution": "O"}, {"num": 0, "solution": "T"}, {"num": 0, "solution": "A"}, {"num": -1, "solution": ""}, {"num": 60, "solution": "T"}, {"num": 0, "solution": "I"}, {"num": 0, "solution": "G"}, {"num": 0, "solution": "E"}, {"num": 61, "solution": "L"}, {"num": 0, "solution": "O"}, {"num": 0, "solution": "E"}, {"num": 0, "solution": "B"}, {"num": -1, "solution": ""}, {"num": 62, "solution": "I"}, {"num": 0, "solution": "S"}, {"num": 0, "solution": "N"}, {"num": 0, "solution": "O"}, {"num": 0, "solution": "T"}, {"num": -1, "solution": ""}, {"num": 63, "solution": "U"}, {"num": 0, "solution": "L"}, {"num": 0, "solution": "A"}, {"num": 0, "solution": "N"}, {"num": 64, "solution": "R"}, {"num": 0, "solution": "U"}, {"num": 0, "solution": "D"}, {"num": 0, "solution": "Y"}, {"num": -1, "solution": ""}, {"num": 65, "solution": "S"}, {"num": 0, "solution": "H"}, {"num": 0, "solution": "E"}, {"num": 0, "solution": "P"}, {"num": 0, "solution": "S"}, {"num": -1, "solution": ""}, {"num": 66, "solution": "M"}, {"num": 0, "solution": "E"}, {"num": 0, "solution": "N"}, {"num": 0, "solution": "D"}], "fill": "----.-----.--------.-----.--------.-----.-----------------..-----.---.-----.------.-------...---.---..---.-------------.---..---.---...-------.------.-----.---.-----..-----------------.-----.--------.-----.--------.-----.----", "title": "NY Times, Thursday, April 8, 1999 ", "notes": "", "author": "David J. Kahn / Will Shortz", "solution": "LOGE.IPASS.TWOSOBIT.NORTE.OATHEERO.MOBIL.MUSESYDNEYPOLLACK..SELIG.ERE.GAELS.REARED.TOOTSIE...NEV.CTR..HOT.DUSTINHOFFMAN.BEN..TIE.EEO...RAINMAN.TORMES.ARMEE.NAH.MENLO..BARRYLEVINSONSLUR.BIOTA.TIGELOEB.ISNOT.ULANRUDY.SHEPS.MEND", "clues": {"down": [{"num": 1, "solution": "LOESS", "clue": "Loamy deposit"}, {"num": 2, "solution": "OBEYER", "clue": "Good dog"}, {"num": 3, "solution": "GIRDLE", "clue": "Slimming device"}, {"num": 4, "solution": "ETONIANS", "clue": "Some English students"}, {"num": 5, "solution": "INMY", "clue": "\"___ Room\" (Beach Boys hit)"}, {"num": 6, "solution": "POOPED", "clue": "Spent"}, {"num": 7, "solution": "ARBOR", "clue": "Shady alcove"}, {"num": 8, "solution": "STILETTO", "clue": "Kind of heel"}, {"num": 9, "solution": "SELL", "clue": "Push, maybe"}, {"num": 10, "solution": "TOMCAT", "clue": "Tabby's mate"}, {"num": 11, "solution": "WAUKESHA", "clue": "Wisconsin city"}, {"num": 12, "solution": "OTS", "clue": "Exciting times in the N.I.T."}, {"num": 13, "solution": "SHE", "clue": "___-wolf"}, {"num": 21, "solution": "EGRET", "clue": "Plume source"}, {"num": 22, "solution": "AGO", "clue": "Earlier"}, {"num": 26, "solution": "LION", "clue": "Brave one"}, {"num": 27, "solution": "SET", "clue": "Harden"}, {"num": 29, "solution": "EVITA", "clue": "1980 Tony winner"}, {"num": 31, "solution": "ORFEO", "clue": "Gluck's \"___ ed Euridice\""}, {"num": 33, "solution": "CHE", "clue": "29-Down role"}, {"num": 35, "solution": "DEAR", "clue": "Precious"}, {"num": 36, "solution": "UNIMBUED", "clue": "Not permeated (with)"}, {"num": 37, "solution": "NINNYISH", "clue": "Silly"}, {"num": 38, "solution": "FERMI", "clue": "1938 Physics Nobelist"}, {"num": 39, "solution": "MOMENTUM", "clue": "Campaign asset"}, {"num": 40, "solution": "BRA", "clue": "Support provider"}, {"num": 44, "solution": "NEARBY", "clue": "Nigh"}, {"num": 45, "solution": "MER", "clue": "Terre's opposite"}, {"num": 46, "solution": "THETOP", "clue": "A lonely place, so they say"}, {"num": 47, "solution": "ENSILE", "clue": "Store, as fodder"}, {"num": 48, "solution": "SLOGAN", "clue": "Ad dressing?"}, {"num": 51, "solution": "ALONE", "clue": "Let ___"}, {"num": 53, "solution": "ONEND", "clue": "Successively"}, {"num": 55, "solution": "RBIS", "clue": "Power stats"}, {"num": 56, "solution": "VATS", "clue": "Tanks"}, {"num": 57, "solution": "SLR", "clue": "Certain camera, for short"}, {"num": 58, "solution": "LOU", "clue": "Baseball's Brock"}], "across": [{"num": 1, "solution": "LOGE", "clue": "Orchestra alternative"}, {"num": 5, "solution": "IPASS", "clue": "Comment around the deck?"}, {"num": 10, "solution": "TWOS", "clue": "Terrible ___"}, {"num": 14, "solution": "OBIT", "clue": "Last words?"}, {"num": 15, "solution": "NORTE", "clue": "Opposite of sur"}, {"num": 16, "solution": "OATH", "clue": "Four-letter word"}, {"num": 17, "solution": "EERO", "clue": "Architect Saarinen"}, {"num": 18, "solution": "MOBIL", "clue": "Company whose logo has a red \"o\""}, {"num": 19, "solution": "MUSE", "clue": "Cogitate"}, {"num": 20, "solution": "SYDNEYPOLLACK", "clue": "Noted director who acted in 30-Across with 35-Across"}, {"num": 23, "solution": "SELIG", "clue": "Bud of baseball"}, {"num": 24, "solution": "ERE", "clue": "Before, once"}, {"num": 25, "solution": "GAELS", "clue": "Isle of Man residents"}, {"num": 28, "solution": "REARED", "clue": "Brought up"}, {"num": 30, "solution": "TOOTSIE", "clue": "See 20-Across"}, {"num": 32, "solution": "NEV", "clue": "Calif. neighbor"}, {"num": 33, "solution": "CTR", "clue": "Midpoint: Abbr."}, {"num": 34, "solution": "HOT", "clue": "On a roll"}, {"num": 35, "solution": "DUSTINHOFFMAN", "clue": "See 20-Across and 54-Across"}, {"num": 40, "solution": "BEN", "clue": "Big ___"}, {"num": 41, "solution": "TIE", "clue": "Link"}, {"num": 42, "solution": "EEO", "clue": "Classified inits."}, {"num": 43, "solution": "RAINMAN", "clue": "See 54-Across"}, {"num": 46, "solution": "TORMES", "clue": "Singer Mel and namesakes"}, {"num": 49, "solution": "ARMEE", "clue": "Napol\u00e9on led one"}, {"num": 50, "solution": "NAH", "clue": "\"Forget it!\""}, {"num": 52, "solution": "MENLO", "clue": "___ Park, N.J."}, {"num": 54, "solution": "BARRYLEVINSON", "clue": "Noted director who acted in 43-Across with 35-Across"}, {"num": 57, "solution": "SLUR", "clue": "Drunk's tipoff"}, {"num": 59, "solution": "BIOTA", "clue": "Plant and animal life"}, {"num": 60, "solution": "TIGE", "clue": "Andrews of \"The Mod Squad\""}, {"num": 61, "solution": "LOEB", "clue": "Money writer Marshall ___"}, {"num": 62, "solution": "ISNOT", "clue": "\"A house ___ a home\""}, {"num": 63, "solution": "ULAN", "clue": "___ Bator"}, {"num": 64, "solution": "RUDY", "clue": "The rich man in \"Rich Man, Poor Man\""}, {"num": 65, "solution": "SHEPS", "clue": "Some guard dogs, for short"}, {"num": 66, "solution": "MEND", "clue": "Get better"}]}, "height": 15}