{"width": 15, "squares": [{"num": 1, "solution": "L"}, {"num": 2, "solution": "I"}, {"num": 3, "solution": "S"}, {"num": 4, "solution": "T"}, {"num": -1, "solution": ""}, {"num": 5, "solution": "T"}, {"num": 6, "solution": "A"}, {"num": 7, "solution": "S"}, {"num": 8, "solution": "T"}, {"num": 9, "solution": "E"}, {"num": -1, "solution": ""}, {"num": 10, "solution": "A"}, {"num": 11, "solution": "T"}, {"num": 12, "solution": "O"}, {"num": 13, "solution": "Z"}, {"num": 14, "solution": "A"}, {"num": 0, "solution": "N"}, {"num": 0, "solution": "A"}, {"num": 0, "solution": "S"}, {"num": -1, "solution": ""}, {"num": 15, "solution": "A"}, {"num": 0, "solution": "T"}, {"num": 0, "solution": "H"}, {"num": 0, "solution": "O"}, {"num": 0, "solution": "L"}, {"num": -1, "solution": ""}, {"num": 16, "solution": "M"}, {"num": 0, "solution": "E"}, {"num": 0, "solution": "R"}, {"num": 0, "solution": "E"}, {"num": 17, "solution": "W"}, {"num": 0, "solution": "H"}, {"num": 0, "solution": "I"}, {"num": 0, "solution": "P"}, {"num": -1, "solution": ""}, {"num": 18, "solution": "P"}, {"num": 0, "solution": "R"}, {"num": 0, "solution": "I"}, {"num": 0, "solution": "V"}, {"num": 0, "solution": "A"}, {"num": 19, "solution": "T"}, {"num": 0, "solution": "E"}, {"num": 0, "solution": "E"}, {"num": 0, "solution": "Y"}, {"num": 0, "solution": "E"}, {"num": 20, "solution": "Y"}, {"num": 0, "solution": "U"}, {"num": 0, "solution": "L"}, {"num": -1, "solution": ""}, {"num": 21, "solution": "M"}, {"num": 0, "solution": "E"}, {"num": 0, "solution": "I"}, {"num": 0, "solution": "R"}, {"num": -1, "solution": ""}, {"num": 22, "solution": "P"}, {"num": 0, "solution": "A"}, {"num": 0, "solution": "N"}, {"num": 0, "solution": "T"}, {"num": -1, "solution": ""}, {"num": -1, "solution": ""}, {"num": 23, "solution": "E"}, {"num": 0, "solution": "M"}, {"num": 0, "solution": "O"}, {"num": 24, "solution": "T"}, {"num": 0, "solution": "E"}, {"num": -1, "solution": ""}, {"num": 25, "solution": "P"}, {"num": 0, "solution": "R"}, {"num": 26, "solution": "E"}, {"num": 0, "solution": "S"}, {"num": 0, "solution": "I"}, {"num": 0, "solution": "D"}, {"num": 0, "solution": "E"}, {"num": 27, "solution": "N"}, {"num": 28, "solution": "T"}, {"num": 29, "solution": "R"}, {"num": 0, "solution": "E"}, {"num": 0, "solution": "R"}, {"num": 0, "solution": "A"}, {"num": 0, "solution": "T"}, {"num": 30, "solution": "E"}, {"num": -1, "solution": ""}, {"num": -1, "solution": ""}, {"num": 31, "solution": "A"}, {"num": 0, "solution": "E"}, {"num": 0, "solution": "S"}, {"num": -1, "solution": ""}, {"num": 32, "solution": "R"}, {"num": 0, "solution": "I"}, {"num": 0, "solution": "O"}, {"num": -1, "solution": ""}, {"num": -1, "solution": ""}, {"num": -1, "solution": ""}, {"num": 33, "solution": "S"}, {"num": 0, "solution": "O"}, {"num": 0, "solution": "L"}, {"num": 34, "solution": "V"}, {"num": 35, "solution": "E"}, {"num": 0, "solution": "R"}, {"num": -1, "solution": ""}, {"num": -1, "solution": ""}, {"num": 36, "solution": "P"}, {"num": 0, "solution": "E"}, {"num": 0, "solution": "N"}, {"num": 0, "solution": "T"}, {"num": 37, "solution": "J"}, {"num": 38, "solution": "A"}, {"num": 39, "solution": "C"}, {"num": 0, "solution": "K"}, {"num": 0, "solution": "O"}, {"num": 0, "solution": "F"}, {"num": 0, "solution": "A"}, {"num": 0, "solution": "L"}, {"num": 0, "solution": "L"}, {"num": 40, "solution": "T"}, {"num": 41, "solution": "R"}, {"num": 0, "solution": "A"}, {"num": 0, "solution": "D"}, {"num": 0, "solution": "E"}, {"num": 0, "solution": "S"}, {"num": 42, "solution": "U"}, {"num": 0, "solution": "G"}, {"num": 0, "solution": "H"}, {"num": 0, "solution": "S"}, {"num": -1, "solution": ""}, {"num": -1, "solution": ""}, {"num": 43, "solution": "R"}, {"num": 0, "solution": "O"}, {"num": 0, "solution": "S"}, {"num": 0, "solution": "I"}, {"num": 0, "solution": "E"}, {"num": 0, "solution": "R"}, {"num": -1, "solution": ""}, {"num": -1, "solution": ""}, {"num": -1, "solution": ""}, {"num": 44, "solution": "D"}, {"num": 0, "solution": "R"}, {"num": 0, "solution": "I"}, {"num": -1, "solution": ""}, {"num": 45, "solution": "M"}, {"num": 46, "solution": "A"}, {"num": 0, "solution": "I"}, {"num": -1, "solution": ""}, {"num": -1, "solution": ""}, {"num": 47, "solution": "D"}, {"num": 0, "solution": "E"}, {"num": 0, "solution": "T"}, {"num": 48, "solution": "A"}, {"num": 49, "solution": "C"}, {"num": 50, "solution": "H"}, {"num": 51, "solution": "O"}, {"num": 0, "solution": "I"}, {"num": 0, "solution": "L"}, {"num": 52, "solution": "R"}, {"num": 0, "solution": "I"}, {"num": 0, "solution": "G"}, {"num": 0, "solution": "G"}, {"num": 53, "solution": "E"}, {"num": 54, "solution": "R"}, {"num": -1, "solution": ""}, {"num": 55, "solution": "S"}, {"num": 0, "solution": "I"}, {"num": 0, "solution": "N"}, {"num": 0, "solution": "A"}, {"num": 0, "solution": "I"}, {"num": -1, "solution": ""}, {"num": -1, "solution": ""}, {"num": 56, "solution": "L"}, {"num": 0, "solution": "A"}, {"num": 0, "solution": "M"}, {"num": 0, "solution": "A"}, {"num": -1, "solution": ""}, {"num": 57, "solution": "N"}, {"num": 0, "solution": "O"}, {"num": 58, "solution": "T"}, {"num": 0, "solution": "E"}, {"num": -1, "solution": ""}, {"num": 59, "solution": "C"}, {"num": 0, "solution": "S"}, {"num": 0, "solution": "T"}, {"num": 60, "solution": "B"}, {"num": 61, "solution": "O"}, {"num": 0, "solution": "O"}, {"num": 0, "solution": "K"}, {"num": 0, "solution": "E"}, {"num": 0, "solution": "D"}, {"num": 62, "solution": "I"}, {"num": 0, "solution": "T"}, {"num": 0, "solution": "O"}, {"num": 0, "solution": "R"}, {"num": -1, "solution": ""}, {"num": 63, "solution": "W"}, {"num": 0, "solution": "H"}, {"num": 0, "solution": "I"}, {"num": 0, "solution": "M"}, {"num": 64, "solution": "R"}, {"num": 0, "solution": "O"}, {"num": 0, "solution": "U"}, {"num": 0, "solution": "E"}, {"num": -1, "solution": ""}, {"num": 65, "solution": "I"}, {"num": 0, "solution": "R"}, {"num": 0, "solution": "E"}, {"num": 0, "solution": "N"}, {"num": 0, "solution": "E"}, {"num": -1, "solution": ""}, {"num": 66, "solution": "I"}, {"num": 0, "solution": "O"}, {"num": 0, "solution": "N"}, {"num": 0, "solution": "A"}, {"num": 67, "solution": "O"}, {"num": 0, "solution": "P"}, {"num": 0, "solution": "T"}, {"num": 0, "solution": "S"}, {"num": -1, "solution": ""}, {"num": 68, "solution": "R"}, {"num": 0, "solution": "A"}, {"num": 0, "solution": "R"}, {"num": 0, "solution": "E"}, {"num": 0, "solution": "E"}, {"num": -1, "solution": ""}, {"num": 69, "solution": "T"}, {"num": 0, "solution": "R"}, {"num": 0, "solution": "O"}, {"num": 0, "solution": "N"}], "fill": "----.-----.--------.-----.--------.-------------.----.----..-----.---------------..---.---...------..-----------------------..------...---.---..---------------.-----..----.----.-------------.--------.-----.--------.-----.----", "title": "NY Times, Thursday, March 27, 2003 ", "notes": "", "author": "David J. Kahn / Will Shortz", "solution": "LIST.TASTE.ATOZANAS.ATHOL.MEREWHIP.PRIVATEEYEYUL.MEIR.PANT..EMOTE.PRESIDENTRERATE..AES.RIO...SOLVER..PENTJACKOFALLTRADESUGHS..ROSIER...DRI.MAI..DETACHOILRIGGER.SINAI..LAMA.NOTE.CSTBOOKEDITOR.WHIMROUE.IRENE.IONAOPTS.RAREE.TRON", "clues": {"down": [{"num": 1, "solution": "LAWYER", "clue": "Nicholson role in \"Easy Rider\""}, {"num": 2, "solution": "INHUME", "clue": "Bury"}, {"num": 3, "solution": "SAILOR", "clue": "Nicholson role in \"The Last Detail\""}, {"num": 4, "solution": "TSP", "clue": "Child's dose, maybe: Abbr."}, {"num": 5, "solution": "TAPE", "clue": "It may be magnetic"}, {"num": 6, "solution": "ATRIP", "clue": "Take ___ (travel)"}, {"num": 7, "solution": "SHIRR", "clue": "Bake, in a way"}, {"num": 8, "solution": "TOV", "clue": "\"Mazel ___!\""}, {"num": 9, "solution": "ELAPSE", "clue": "Go by"}, {"num": 10, "solution": "AMEND", "clue": "Add to or subtract from"}, {"num": 11, "solution": "TEETERED", "clue": "Was indecisive"}, {"num": 12, "solution": "ORY", "clue": "Suffix with access"}, {"num": 13, "solution": "ZEE", "clue": "Zuyder ___"}, {"num": 19, "solution": "TAIS", "clue": "See 45-Across"}, {"num": 21, "solution": "METOO", "clue": "\"I feel the same way\""}, {"num": 24, "solution": "TASKS", "clue": "Undertakings"}, {"num": 26, "solution": "EARLS", "clue": "Viscounts' superiors"}, {"num": 27, "solution": "NINE", "clue": "Musical with the song \"Be Italian\""}, {"num": 28, "solution": "TOTS", "clue": "Day-care charges"}, {"num": 30, "solution": "ELF", "clue": "Gnome"}, {"num": 34, "solution": "VARIG", "clue": "Carrier to 32-Across"}, {"num": 35, "solution": "ELO", "clue": "\"Do Ya\" grp."}, {"num": 36, "solution": "PARTI", "clue": "Start of a long story?"}, {"num": 37, "solution": "JUDO", "clue": "Olympic event since 1972"}, {"num": 38, "solution": "AGRI", "clue": "Cultural beginning?"}, {"num": 39, "solution": "CHILLOUT", "clue": "Relax"}, {"num": 40, "solution": "TID", "clue": "Pharmacist's abbr."}, {"num": 41, "solution": "REESE", "clue": "Teammate of Snider and Hodges"}, {"num": 45, "solution": "MIME", "clue": "Street performer"}, {"num": 46, "solution": "AGADIR", "clue": "Moroccan port"}, {"num": 48, "solution": "ANCHOR", "clue": "Nicholson role in \"Broadcast News\""}, {"num": 49, "solution": "CASINO", "clue": "Where a dealer deals"}, {"num": 50, "solution": "HITMAN", "clue": "Nicholson role in \"Prizzi's Honor\""}, {"num": 52, "solution": "RAKES", "clue": "49-Down tools"}, {"num": 53, "solution": "ENTER", "clue": "Join"}, {"num": 54, "solution": "ROONE", "clue": "News exec Arledge"}, {"num": 58, "solution": "TREE", "clue": "Gallows"}, {"num": 60, "solution": "BRO", "clue": "Dude"}, {"num": 61, "solution": "OOP", "clue": "Alley ___"}, {"num": 62, "solution": "IRA", "clue": "Author Levin"}, {"num": 63, "solution": "WIT", "clue": "Raconteur's asset"}], "across": [{"num": 1, "solution": "LIST", "clue": "Directory"}, {"num": 5, "solution": "TASTE", "clue": "Opposite of kitsch"}, {"num": 10, "solution": "ATOZ", "clue": "Exhaustive"}, {"num": 14, "solution": "ANAS", "clue": "Comic Gasteyer and others"}, {"num": 15, "solution": "ATHOL", "clue": "Playwright Fugard"}, {"num": 16, "solution": "MERE", "clue": "Nothing but"}, {"num": 17, "solution": "WHIP", "clue": "Senate V.I.P."}, {"num": 18, "solution": "PRIVATEEYE", "clue": "Nicholson role in \"Chinatown\""}, {"num": 20, "solution": "YUL", "clue": "Gertrude's 1951 Broadway co-star"}, {"num": 21, "solution": "MEIR", "clue": "Dayan colleague"}, {"num": 22, "solution": "PANT", "clue": "___ cuffs"}, {"num": 23, "solution": "EMOTE", "clue": "Play too broadly"}, {"num": 25, "solution": "PRESIDENT", "clue": "Nicholson role in \"Mars Attacks!\""}, {"num": 29, "solution": "RERATE", "clue": "Change from AA to AAA, e.g."}, {"num": 31, "solution": "AES", "clue": "Two-time Dem. nominee"}, {"num": 32, "solution": "RIO", "clue": "Where Sugarloaf Mountain is"}, {"num": 33, "solution": "SOLVER", "clue": "You, for one"}, {"num": 36, "solution": "PENT", "clue": "___-up (confined)"}, {"num": 37, "solution": "JACKOFALLTRADES", "clue": "Apt title for this puzzle"}, {"num": 42, "solution": "UGHS", "clue": "Words with grimaces"}, {"num": 43, "solution": "ROSIER", "clue": "More favorable"}, {"num": 44, "solution": "DRI", "clue": "Soft & ___ (Gillette product)"}, {"num": 45, "solution": "MAI", "clue": "With 19-Down, rum drinks"}, {"num": 47, "solution": "DETACH", "clue": "Unfasten"}, {"num": 51, "solution": "OILRIGGER", "clue": "Nicholson role in \"Five Easy Pieces\""}, {"num": 55, "solution": "SINAI", "clue": "Mideast hot spot"}, {"num": 56, "solution": "LAMA", "clue": "Priest from the East"}, {"num": 57, "solution": "NOTE", "clue": "Melody part"}, {"num": 59, "solution": "CST", "clue": "Iowa hrs."}, {"num": 60, "solution": "BOOKEDITOR", "clue": "Nicholson role in \"Wolf\""}, {"num": 63, "solution": "WHIM", "clue": "Fancy"}, {"num": 64, "solution": "ROUE", "clue": "Libertine"}, {"num": 65, "solution": "IRENE", "clue": "\"Goodnight ___\""}, {"num": 66, "solution": "IONA", "clue": "Hebrides island"}, {"num": 67, "solution": "OPTS", "clue": "Picks"}, {"num": 68, "solution": "RAREE", "clue": "Street show"}, {"num": 69, "solution": "TRON", "clue": "Disney film with a video-game contest"}]}, "height": 15}