{"width": 15, "squares": [{"num": 1, "solution": "N"}, {"num": 2, "solution": "E"}, {"num": 3, "solution": "E"}, {"num": 4, "solution": "D"}, {"num": 5, "solution": "T"}, {"num": 6, "solution": "O"}, {"num": 7, "solution": "K"}, {"num": 8, "solution": "N"}, {"num": 9, "solution": "O"}, {"num": 10, "solution": "W"}, {"num": 11, "solution": "B"}, {"num": 12, "solution": "A"}, {"num": 13, "solution": "S"}, {"num": 14, "solution": "I"}, {"num": 15, "solution": "S"}, {"num": 16, "solution": "E"}, {"num": 0, "solution": "D"}, {"num": 0, "solution": "U"}, {"num": 0, "solution": "C"}, {"num": 0, "solution": "A"}, {"num": 0, "solution": "T"}, {"num": 0, "solution": "I"}, {"num": 0, "solution": "O"}, {"num": 0, "solution": "N"}, {"num": 0, "solution": "A"}, {"num": 0, "solution": "L"}, {"num": 0, "solution": "F"}, {"num": 0, "solution": "I"}, {"num": 0, "solution": "L"}, {"num": 0, "solution": "M"}, {"num": 17, "solution": "A"}, {"num": 0, "solution": "G"}, {"num": 0, "solution": "R"}, {"num": 0, "solution": "E"}, {"num": 0, "solution": "E"}, {"num": 0, "solution": "T"}, {"num": 0, "solution": "O"}, {"num": 0, "solution": "D"}, {"num": 0, "solution": "I"}, {"num": 0, "solution": "S"}, {"num": 0, "solution": "A"}, {"num": 0, "solution": "G"}, {"num": 0, "solution": "R"}, {"num": 0, "solution": "E"}, {"num": 0, "solution": "E"}, {"num": 18, "solution": "T"}, {"num": 0, "solution": "E"}, {"num": 0, "solution": "A"}, {"num": 0, "solution": "L"}, {"num": -1, "solution": ""}, {"num": 19, "solution": "O"}, {"num": 0, "solution": "S"}, {"num": 0, "solution": "S"}, {"num": 0, "solution": "O"}, {"num": -1, "solution": ""}, {"num": 20, "solution": "S"}, {"num": 0, "solution": "H"}, {"num": 0, "solution": "O"}, {"num": 0, "solution": "R"}, {"num": 0, "solution": "E"}, {"num": -1, "solution": ""}, {"num": 21, "solution": "S"}, {"num": 0, "solution": "I"}, {"num": 0, "solution": "L"}, {"num": 22, "solution": "T"}, {"num": -1, "solution": ""}, {"num": 23, "solution": "K"}, {"num": 0, "solution": "A"}, {"num": 0, "solution": "N"}, {"num": -1, "solution": ""}, {"num": 24, "solution": "T"}, {"num": 0, "solution": "A"}, {"num": 0, "solution": "C"}, {"num": -1, "solution": ""}, {"num": -1, "solution": ""}, {"num": -1, "solution": ""}, {"num": -1, "solution": ""}, {"num": 25, "solution": "L"}, {"num": 0, "solution": "S"}, {"num": 0, "solution": "A"}, {"num": 26, "solution": "T"}, {"num": -1, "solution": ""}, {"num": 27, "solution": "T"}, {"num": 0, "solution": "R"}, {"num": 28, "solution": "S"}, {"num": -1, "solution": ""}, {"num": 29, "solution": "N"}, {"num": 0, "solution": "C"}, {"num": 30, "solution": "A"}, {"num": 31, "solution": "R"}, {"num": -1, "solution": ""}, {"num": -1, "solution": ""}, {"num": -1, "solution": ""}, {"num": -1, "solution": ""}, {"num": 32, "solution": "P"}, {"num": 0, "solution": "H"}, {"num": 33, "solution": "D"}, {"num": -1, "solution": ""}, {"num": 34, "solution": "O"}, {"num": 0, "solution": "N"}, {"num": 35, "solution": "E"}, {"num": 0, "solution": "I"}, {"num": 0, "solution": "O"}, {"num": 0, "solution": "T"}, {"num": 0, "solution": "A"}, {"num": 36, "solution": "I"}, {"num": 37, "solution": "S"}, {"num": 38, "solution": "A"}, {"num": 39, "solution": "D"}, {"num": 0, "solution": "O"}, {"num": 0, "solution": "R"}, {"num": 0, "solution": "A"}, {"num": -1, "solution": ""}, {"num": 40, "solution": "L"}, {"num": 0, "solution": "E"}, {"num": 0, "solution": "T"}, {"num": 0, "solution": "S"}, {"num": 0, "solution": "S"}, {"num": 0, "solution": "E"}, {"num": 0, "solution": "E"}, {"num": 41, "solution": "S"}, {"num": 0, "solution": "I"}, {"num": 0, "solution": "S"}, {"num": 0, "solution": "E"}, {"num": 0, "solution": "N"}, {"num": 0, "solution": "O"}, {"num": 0, "solution": "R"}, {"num": -1, "solution": ""}, {"num": 42, "solution": "L"}, {"num": 0, "solution": "E"}, {"num": 0, "solution": "A"}, {"num": -1, "solution": ""}, {"num": -1, "solution": ""}, {"num": -1, "solution": ""}, {"num": -1, "solution": ""}, {"num": 43, "solution": "O"}, {"num": 0, "solution": "T"}, {"num": 0, "solution": "I"}, {"num": 0, "solution": "C"}, {"num": -1, "solution": ""}, {"num": 44, "solution": "E"}, {"num": 0, "solution": "T"}, {"num": 45, "solution": "C"}, {"num": -1, "solution": ""}, {"num": 46, "solution": "R"}, {"num": 0, "solution": "I"}, {"num": 47, "solution": "N"}, {"num": 48, "solution": "G"}, {"num": -1, "solution": ""}, {"num": -1, "solution": ""}, {"num": -1, "solution": ""}, {"num": -1, "solution": ""}, {"num": 49, "solution": "T"}, {"num": 0, "solution": "R"}, {"num": 50, "solution": "E"}, {"num": -1, "solution": ""}, {"num": 51, "solution": "A"}, {"num": 0, "solution": "R"}, {"num": 52, "solution": "P"}, {"num": -1, "solution": ""}, {"num": 53, "solution": "L"}, {"num": 0, "solution": "A"}, {"num": 0, "solution": "R"}, {"num": 54, "solution": "D"}, {"num": -1, "solution": ""}, {"num": 55, "solution": "R"}, {"num": 56, "solution": "A"}, {"num": 0, "solution": "W"}, {"num": 0, "solution": "E"}, {"num": 0, "solution": "R"}, {"num": -1, "solution": ""}, {"num": 57, "solution": "G"}, {"num": 0, "solution": "A"}, {"num": 0, "solution": "I"}, {"num": 58, "solution": "A"}, {"num": -1, "solution": ""}, {"num": 59, "solution": "S"}, {"num": 0, "solution": "E"}, {"num": 0, "solution": "A"}, {"num": 60, "solution": "M"}, {"num": 61, "solution": "C"}, {"num": 0, "solution": "L"}, {"num": 0, "solution": "E"}, {"num": 0, "solution": "A"}, {"num": 0, "solution": "R"}, {"num": 62, "solution": "A"}, {"num": 0, "solution": "N"}, {"num": 0, "solution": "D"}, {"num": 0, "solution": "P"}, {"num": 0, "solution": "R"}, {"num": 63, "solution": "E"}, {"num": 0, "solution": "S"}, {"num": 0, "solution": "E"}, {"num": 0, "solution": "N"}, {"num": 0, "solution": "T"}, {"num": 64, "solution": "P"}, {"num": 0, "solution": "E"}, {"num": 0, "solution": "R"}, {"num": 0, "solution": "S"}, {"num": 0, "solution": "O"}, {"num": 0, "solution": "N"}, {"num": 0, "solution": "A"}, {"num": 0, "solution": "L"}, {"num": 0, "solution": "E"}, {"num": 0, "solution": "F"}, {"num": 0, "solution": "F"}, {"num": 0, "solution": "E"}, {"num": 0, "solution": "C"}, {"num": 0, "solution": "T"}, {"num": 0, "solution": "S"}, {"num": 65, "solution": "T"}, {"num": 0, "solution": "R"}, {"num": 0, "solution": "E"}, {"num": 0, "solution": "E"}, {"num": 0, "solution": "L"}, {"num": 0, "solution": "I"}, {"num": 0, "solution": "N"}, {"num": 0, "solution": "E"}, {"num": 0, "solution": "D"}, {"num": 0, "solution": "S"}, {"num": 0, "solution": "T"}, {"num": 0, "solution": "R"}, {"num": 0, "solution": "E"}, {"num": 0, "solution": "E"}, {"num": 0, "solution": "T"}], "fill": "-------------------------------------------------.----.-----.----.---.---....----.---.----....---.--------------.--------------.---....----.---.----....---.---.----.-----.----.-------------------------------------------------", "title": "NY Times, Friday, September 2, 2011 ", "notes": "", "author": "Tim Croce / Will Shortz", "solution": "NEEDTOKNOWBASISEDUCATIONALFILMAGREETODISAGREETEAL.OSSO.SHORE.SILT.KAN.TAC....LSAT.TRS.NCAR....PHD.ONEIOTAISADORA.LETSSEESISENOR.LEA....OTIC.ETC.RING....TRE.ARP.LARD.RAWER.GAIA.SEAMCLEARANDPRESENTPERSONALEFFECTSTREELINEDSTREET", "clues": {"down": [{"num": 1, "solution": "NEAT", "clue": "Ingenious"}, {"num": 2, "solution": "EDGES", "clue": "Ball's lack"}, {"num": 3, "solution": "EURAIL", "clue": "Continental pass provider"}, {"num": 4, "solution": "DCELLS", "clue": "Common flashlight fillers"}, {"num": 5, "solution": "TAE", "clue": "South Korea's Roh ___ Woo"}, {"num": 6, "solution": "OTTO", "clue": "Cartoon busman Mann"}, {"num": 7, "solution": "KIOSK", "clue": "Small business site"}, {"num": 8, "solution": "NODSAT", "clue": "Gives a passing acknowledgment"}, {"num": 9, "solution": "ONIONROLL", "clue": "Piquant sandwich base"}, {"num": 10, "solution": "WAS", "clue": "\"Time ___ ...\""}, {"num": 11, "solution": "BLAST", "clue": "Firing result"}, {"num": 12, "solution": "AFGHANIS", "clue": "Kandahar cash"}, {"num": 13, "solution": "SIROCCOS", "clue": "Dust-laden winds"}, {"num": 14, "solution": "ILER", "clue": "Soprano player Robert"}, {"num": 15, "solution": "SMEE", "clue": "Hook accompanier"}, {"num": 22, "solution": "TAPON", "clue": "Hit lightly"}, {"num": 26, "solution": "THROE", "clue": "Painful struggle"}, {"num": 28, "solution": "SNEER", "clue": "Look bad?"}, {"num": 30, "solution": "ATE", "clue": "Put down"}, {"num": 31, "solution": "RAE", "clue": "Movie heroine Norma ___ Webster"}, {"num": 33, "solution": "DARTAGNAN", "clue": "Dumas hero"}, {"num": 35, "solution": "ETAIL", "clue": "Some cashless commerce"}, {"num": 36, "solution": "ISO", "clue": "Prefix with -meric"}, {"num": 37, "solution": "SIT", "clue": "Get on the bottom?"}, {"num": 38, "solution": "ASITWERE", "clue": "Seemingly"}, {"num": 39, "solution": "DECREASE", "clue": "Cut"}, {"num": 45, "solution": "CRADLE", "clue": "Protect"}, {"num": 47, "solution": "NASSER", "clue": "Six-Day War figure"}, {"num": 48, "solution": "GREECE", "clue": "Attic locale"}, {"num": 50, "solution": "ERROL", "clue": "Owl in Harry Potter tales"}, {"num": 52, "solution": "PIPED", "clue": "Brought (in), as music"}, {"num": 54, "solution": "DANTE", "clue": "He met Charon in the underworld"}, {"num": 55, "solution": "RCPT", "clue": "Return request: Abbr."}, {"num": 56, "solution": "ALER", "clue": "A, Jay or Ray"}, {"num": 58, "solution": "ARFS", "clue": "Boxer rebellion cries?"}, {"num": 60, "solution": "MTST", "clue": "___ Mary's (L.A. college)"}, {"num": 62, "solution": "ANI", "clue": "Black bird"}, {"num": 63, "solution": "EFT", "clue": "Young pond dweller"}], "across": [{"num": 1, "solution": "NEEDTOKNOWBASIS", "clue": "Sensitive information is often shared on it"}, {"num": 16, "solution": "EDUCATIONALFILM", "clue": "Thing rolled in a classroom"}, {"num": 17, "solution": "AGREETODISAGREE", "clue": "Continue cordially despite differences"}, {"num": 18, "solution": "TEAL", "clue": "Cousin of a canvasback"}, {"num": 19, "solution": "OSSO", "clue": "Scapola or clavicola"}, {"num": 20, "solution": "SHORE", "clue": "It gets lapped a lot"}, {"num": 21, "solution": "SILT", "clue": "Potential mouth choker"}, {"num": 23, "solution": "KAN", "clue": "Agricultural Hall of Fame locale: Abbr."}, {"num": 24, "solution": "TAC", "clue": "Certain X or O"}, {"num": 25, "solution": "LSAT", "clue": "It includes an analytical reasoning sect."}, {"num": 27, "solution": "TRS", "clue": "___-80 (old computer)"}, {"num": 29, "solution": "NCAR", "clue": "Nascar Hall of Fame locale: Abbr."}, {"num": 32, "solution": "PHD", "clue": "A good defense may result in it, briefly"}, {"num": 34, "solution": "ONEIOTA", "clue": "A wee bit"}, {"num": 36, "solution": "ISADORA", "clue": "1968 title role for Vanessa Redgrave"}, {"num": 40, "solution": "LETSSEE", "clue": "\"Thinking ...\""}, {"num": 41, "solution": "SISENOR", "clue": "Chihuahua assent"}, {"num": 42, "solution": "LEA", "clue": "Idyllic place"}, {"num": 43, "solution": "OTIC", "clue": "___ suspension (ear drops)"}, {"num": 44, "solution": "ETC", "clue": "\"And that sort of thing\": Abbr."}, {"num": 46, "solution": "RING", "clue": "Evidence of some growth"}, {"num": 49, "solution": "TRE", "clue": "One-third of nove"}, {"num": 51, "solution": "ARP", "clue": "\"Configuration\" artist"}, {"num": 53, "solution": "LARD", "clue": "Enrich"}, {"num": 55, "solution": "RAWER", "clue": "Not as experienced"}, {"num": 57, "solution": "GAIA", "clue": "Earth as an organism"}, {"num": 59, "solution": "SEAM", "clue": "Place for a rip"}, {"num": 61, "solution": "CLEARANDPRESENT", "clue": "Like real danger"}, {"num": 64, "solution": "PERSONALEFFECTS", "clue": "Toiletries and such"}, {"num": 65, "solution": "TREELINEDSTREET", "clue": "Feature of many a residential neighborhood"}]}, "height": 15}